shops_nocodb_updater/__init__.py
shops_nocodb_updater/client.py
shops_nocodb_updater/models/__init__.py
shops_nocodb_updater/models/base.py
shops_nocodb_updater/models/mapping.py
shops_nocodb_updater/models/shop_models.py
shops_nocodb_updater/models/types.py
shops_nocodb_updater/utils.py
shops_nocodb_updater-2.5.1.dist-info/METADATA
shops_nocodb_updater-2.5.1.dist-info/WHEEL
shops_nocodb_updater-2.5.1.dist-info/RECORD
