Metadata-Version: 2.4
Name: shops_nocodb_updater
Version: 2.5.1
Summary: Verifying telegram user token.
Author: Pavel Mulin
Author-email: pavel@tg-shops.com
Classifier: Programming Language :: Python :: 2
Classifier: Programming Language :: Python :: 2.7
Classifier: Programming Language :: Python :: 3
Classifier: Programming Language :: Python :: 3.4
Classifier: Programming Language :: Python :: 3.5
Classifier: Programming Language :: Python :: 3.6
Classifier: Programming Language :: Python :: 3.7
Classifier: Programming Language :: Python :: 3.8
Classifier: Programming Language :: Python :: 3.9
Classifier: Programming Language :: Python :: 3.10
Classifier: Programming Language :: Python :: 3.11
Classifier: Programming Language :: Python :: 3.12
Classifier: Programming Language :: Python :: 3.13
Classifier: Programming Language :: Python :: 3.14
Requires-Dist: aiofiles (>=24.1.0)
Requires-Dist: httpx (>=0.23.0)
Requires-Dist: pillow (>=11.1.0)
Requires-Dist: pycountry (>=24.6.1)
Requires-Dist: pydantic (>=1.10.0)
